xstate_statemachine/__init__.py
xstate_statemachine/base_interpreter.py
xstate_statemachine/cli/__init__.py
xstate_statemachine/cli/__main__.py
xstate_statemachine/cli/args.py
xstate_statemachine/cli/extractor.py
xstate_statemachine/cli/generator.py
xstate_statemachine/cli/utils.py
xstate_statemachine/events.py
xstate_statemachine/exceptions.py
xstate_statemachine/factory.py
xstate_statemachine/interpreter.py
xstate_statemachine/logger.py
xstate_statemachine/logic_loader.py
xstate_statemachine/machine_logic.py
xstate_statemachine/models.py
xstate_statemachine/plugins.py
xstate_statemachine/resolver.py
xstate_statemachine/sync_interpreter.py
xstate_statemachine/task_manager.py
xstate_statemachine-0.4.2.dist-info/entry_points.txt
xstate_statemachine-0.4.2.dist-info/LICENSE
xstate_statemachine-0.4.2.dist-info/METADATA
xstate_statemachine-0.4.2.dist-info/WHEEL
xstate_statemachine-0.4.2.dist-info/RECORD
