Metadata-Version: 2.3
Name: xstate-statemachine
Version: 0.4.2
Summary: A robust Python library for parsing and running XState JSON state machines.
License: MIT
Author: Basil T T
Author-email: tt.basil@gmail.com
Requires-Python: >=3.8
Classifier: Programming Language :: Python :: 3
Classifier: License :: OSI Approved :: MIT License
Classifier: Operating System :: OS Independent
Classifier: Intended Audience :: Developers
Classifier: Topic :: Software Development :: Libraries :: Python Modules
Project-URL: Bug Tracker, https://github.com/basiltt/xstate-statemachine/issues
Project-URL: Homepage, https://github.com/basiltt/xstate-statemachine
